__init__.py
errors.py
ez_setup.py
login.py
restfulfactory.py
setup.py
devilryrestfullib.egg-info/PKG-INFO
devilryrestfullib.egg-info/SOURCES.txt
devilryrestfullib.egg-info/dependency_links.txt
devilryrestfullib.egg-info/requires.txt
devilryrestfullib.egg-info/top_level.txt
examples/duckburghexample.py
examples/ifiscenario.py
examples/minimal.py
examples/periodstats.py
examples/uiodata.py