Metadata-Version: 1.0
Name: devilryrestfullib
Version: 0.3
Summary: Devilry RESTful client library.
Home-page: http://devilry.org
Author: The Devilry developers
Author-email: UNKNOWN
License: BSD
Platform: UNKNOWN
